[
  {
    "Id": "26435",
    "ThreadId": "8092",
    "Html": "\r\nI was turned on to this website today and absolutely LOVE YOU PEOPLE! Your controls are and actual answer to prayer, believe it or not. I am going to point everyone I know straight here who needs this kind of excellent stuff!<br />Awesome!!!<br /><br />I do have a question:<br />When I attempt to set the gradient High and Low settings to Transparent in the Gradient Navigation Button I do not get Transparent I get white, any ideas why? <br /><br />Would greatly appreciate some direction.<br /><br />God Bless,<br /><br />Brenton<br />",
    "PostedDate": "2007-03-12T08:30:05.11-07:00",
    "UserRole": null,
    "MarkedAsAnswerDate": null
  }
]